economic_complexity/__init__.py
economic_complexity/complexity.py
economic_complexity/cross_space.py
economic_complexity/polars/__init__.py
economic_complexity/polars/complexity.py
economic_complexity/polars/product_space.py
economic_complexity/polars/rca.py
economic_complexity/polars/run.py
economic_complexity/product_space.py
economic_complexity/rca.py
economic_complexity/subnational.py
economic_complexity-0.3.0.dist-info/LICENSE
economic_complexity-0.3.0.dist-info/METADATA
economic_complexity-0.3.0.dist-info/WHEEL
economic_complexity-0.3.0.dist-info/RECORD
