Metadata-Version: 2.3
Name: economic-complexity
Version: 0.3.0
Summary: Functions to calculate Economic Complexity indicators.
License: MIT
Author: Jelmy Hermosilla
Author-email: jelmy@datawheel.us
Maintainer: Francisco Abarzua
Maintainer-email: francisco@datawheel.us
Requires-Python: >=3.9, <4.0
Classifier: License :: OSI Approved :: MIT License
Classifier: Programming Language :: Python :: 3
Classifier: Programming Language :: Python :: 3.9
Classifier: Programming Language :: Python :: 3.10
Classifier: Programming Language :: Python :: 3.11
Classifier: Programming Language :: Python :: 3.12
Classifier: Programming Language :: Python :: 3.13
Classifier: Topic :: Software Development :: Libraries :: Python Modules
Provides-Extra: pandas
Provides-Extra: polars
Requires-Dist: pandas (>=1.5.0,<3.0.0) ; extra == "pandas"
Requires-Dist: polars (>=1.0.0) ; extra == "polars"
Project-URL: Repository, https://github.com/Datawheel/py-economic-complexity
